vscode/__init__.py
vscode/__main__.py
vscode/utils.py
vscode_dev-0.1.1.dist-info/METADATA
vscode_dev-0.1.1.dist-info/WHEEL
vscode_dev-0.1.1.dist-info/licenses/LICENSE
vscode_dev-0.1.1.dist-info/RECORD
