Metadata-Version: 2.1
Name: vscode.dev
Version: 0.1.1
Project-URL: Homepage, https://github.com/billyeatcookies/vscode-dev
Project-URL: Bug Tracker, https://github.com/billyeatcookies/vscode-dev/issues
Author-email: Billy <billydevbusiness@gmail.com>
License-Expression: MIT
License-File: LICENSE
Classifier: License :: OSI Approved :: MIT License
Classifier: Operating System :: Microsoft :: Windows
Classifier: Programming Language :: Python :: 3
Requires-Python: >=3.10
